Metadata-Version: 1.0
Name: googlegantt
Version: 0.6.1
Summary: Produce Gantt charts using the Google Charts API
Home-page: UNKNOWN
Author: Adam Bard
Author-email: adam@adambard.com
License: MIT
Platform: UNKNOWN
